chalkit/__init__.py
chalkit/editor.py
chalkit/git_commit.py
chalkit/main.py
chalkit/rreset.py
chalkit/setup.py
chalkit-1.1.0.dist-info/entry_points.txt
chalkit-1.1.0.dist-info/WHEEL
chalkit-1.1.0.dist-info/METADATA
chalkit-1.1.0.dist-info/RECORD
