Metadata-Version: 2.1
Name: chalkit
Version: 1.1.0
Summary: CLI tool to write and save new ideas by just opening your terminal!
Author: Anurag-gg
Author-email: dsanurag520@gmail.com
Requires-Python: >=3.8,<4.0
Classifier: Programming Language :: Python :: 3
Classifier: Programming Language :: Python :: 3.10
Classifier: Programming Language :: Python :: 3.8
Classifier: Programming Language :: Python :: 3.9
Requires-Dist: appdirs (>=1.4.4,<2.0.0)
Requires-Dist: typer[all] (>=0.4.1,<0.5.0)
